[{"Variablen":"HeightafterHeat2_UPPER","Value":0.6626},{"Variablen":"Prüfer_UPPER_KOßE","Value":0.0625},{"Variablen":"UpsettingTransferTime1_UPPER","Value":0.0494},{"Variablen":"Heat1TempTime_UPPER","Value":0.0293},{"Variablen":"ODbeforeHeat2_UPPER","Value":0.024},{"Variablen":"UpsettingTransferTime2_UPPER","Value":0.0231},{"Variablen":"Heat2TempTime_UPPER","Value":0.021},{"Variablen":"Prüfer_LOWER_SCHMIDTMAR","Value":0.0184},{"Variablen":"UpsettingToolTemp1_UPPER","Value":0.018},{"Variablen":"UpsettingTempTime1_UPPER","Value":0.0176}]
